freshlinks/__init__.py
freshlinks/__main__.py
freshlinks/cache.py
freshlinks/canonicalize.py
freshlinks/py.typed
freshlinks/scraper.py
freshlinks-1.0.0.dist-info/METADATA
freshlinks-1.0.0.dist-info/WHEEL
freshlinks-1.0.0.dist-info/top_level.txt
freshlinks-1.0.0.dist-info/RECORD
